bincombo.py
bincombo-0.2.0.dist-info/LICENSE
bincombo-0.2.0.dist-info/METADATA
bincombo-0.2.0.dist-info/WHEEL
bincombo-0.2.0.dist-info/RECORD
