Metadata-Version: 2.1
Name: bincombo
Version: 0.2.0
Summary: Make any type binary-combinable with a single line of code.
Home-page: https://github.com/bob1de/python-bincombo
License: MIT
Author: Robert Schindler
Author-email: dev@bob1.de
Requires-Python: >=3.7,<4.0
Classifier: License :: OSI Approved :: MIT License
Classifier: Programming Language :: Python :: 3
Classifier: Programming Language :: Python :: 3.7
Classifier: Programming Language :: Python :: 3.8
Classifier: Programming Language :: Python :: 3.9
Classifier: Programming Language :: Python :: 3.10
Classifier: Programming Language :: Python :: 3.11
